Workbook

Sheet 1. Hardware Sizing
A1: VRAM SIZING CALCULATOR
A2: Yellow cells = user inputs (edit freely); blue cells = computed formulas
A3: Parameter | B3: FP16 | C3: INT4 | D3: Note
A4: [INPUT] Parameters (billions) | B4: 70 | C4: 70 | D4: Model parameter count
A5: [INPUT] Bytes per parameter (model weights) | B5: 2 | C5: 0.5 | D5: FP16 = 2, INT8 = 1, INT4 = 0.5
A6: Model size (GiB) | B6: =B4*1000000000*B5/(1024*1024*1024) | C6: =C4*1000000000*C5/(1024*1024*1024) | D6: params * 1e9 * bytes_per_param / 1024^3
A8: --- KV Cache (per request) ---
A9: [INPUT] Layers | B9: 80 | C9: 80 | D9: Number of transformer layers
A10: [INPUT] head_dim | B10: 128 | C10: 128 | D10: hidden_size / num_attention_heads
A11: [INPUT] num_kv_heads | B11: 8 | C11: 8 | D11: KV-head groups (GQA); equals num_heads if MHA
A12: [INPUT] seq_len (tokens) | B12: 2048 | C12: 2048 | D12: Average request length in tokens
A13: [INPUT] KV cache dtype (bytes per element) | B13: 2 | C13: 2 | D13: FP16 = 2, INT8 = 1, INT4 = 0.5
A14: KV Cache per request (MiB) | B14: =2*B9*B11*B10*B12*B13/(1024*1024) | C14: =2*C9*C11*C10*C12*C13/(1024*1024) | D14: 2 * layers * kv_heads * head_dim * seq_len * dtype / 1024^2
A16: --- Throughput & Concurrency ---
A17: [INPUT] Target RPM | B17: 1000 | C17: 1000 | D17: Throughput requirement
A18: Target RPS | B18: =B17/60 | C18: =C17/60 | D18: RPM / 60
A19: [INPUT] Average latency (sec) | B19: 2 | C19: 2 | D19: Expected inference latency per request
A20: Concurrency (simultaneous requests) | B20: =ROUND(B18*B19,0) | C20: =ROUND(C18*C19,0) | D20: RPS * Latency (Little's Law)
A21: KV Cache total (GiB) | B21: =B14*B20/1024 | C21: =C14*C20/1024 | D21: KV_per_request_MiB * concurrency / 1024
A23: TOTAL VRAM (GiB) | B23: =B6+B21 | C23: =C6+C21 | D23: Model_GiB + KV_total_GiB
A26: GPU CATALOGUE
A27: Edit VRAM / TFLOPS to match your hardware; GPU requirement formulas reference these cells
A28: GPU | B28: VRAM (GiB) | C28: FP16 TFLOPS | D28: Note
A29: NVIDIA A100 80 GiB (SXM) | B29: 80 | C29: 312 | D29: Best for large models
A30: NVIDIA A100 40 GiB (PCIe) | B30: 40 | C30: 312 | D30: VRAM-limited
A31: NVIDIA T4 16 GiB | B31: 16 | C31: 65 | D31: Budget inference
A32: NVIDIA L4 24 GiB | B32: 24 | C32: 121 | D32: Inference-optimized
A33: NVIDIA H100 80 GiB (SXM) | B33: 80 | C33: 990 | D33: Top-tier performance
A35: GPU REQUIREMENTS
A36: GPUs/replica = CEILING(Total VRAM / GPU VRAM from catalogue); Replicas = user input
A37: Configuration | B37: GPUs per replica | C37: [INPUT] Replicas | D37: Total GPUs | E37: Note
A38: FP16 on A100-80 GiB | B38: =CEILING(B23/B29,1) | C38: 6 | D38: =B38*C38 | E38: Tensor Parallel across GPUs
A39: FP16 on A100-40 GiB | B39: =CEILING(B23/B30,1) | C39: 6 | D39: =B39*C39 | E39: Too many GPUs, inefficient
A40: FP16 on L4-24 GiB | B40: =CEILING(B23/B32,1) | C40: 6 | D40: =B40*C40 | E40: Very complex configuration
A41: INT4 on A100-80 GiB | B41: =CEILING(C23/B29,1) | C41: 4 | D41: =B41*C41 | E41: Fits on 1 GPU; 4 replicas enough
A42: INT4 on L4-24 GiB | B42: =CEILING(C23/B32,1) | C42: 5 | D42: =B42*C42 | E42: 2 GPUs in TP; 5 replicas
A43: INT4 on T4-16 GiB | B43: =CEILING(C23/B31,1) | C43: 6 | D43: =B43*C43 | E43: Low throughput; not recommended

Sheet 2. Cloud Comparison
A1: CLOUD COST COMPARISON
A2: Yellow cells = user inputs; blue cells = computed formulas
A3: Yandex Cloud - GPU Instances (price per 1 GPU/hour)
A4: GPU | B4: VRAM (GiB) | C4: Price (RUB/hr) | D4: Price (USD/hr) | E4: Note
A5: NVIDIA A100 80 GiB | B5: 80 | C5: 538 | D5: =C5/$B$9 | E5: gpu-standard-v3
A6: NVIDIA T4 16 GiB | B6: 16 | C6: 134 | D6: =C6/$B$9 | E6: g1/g2 series
A7: NVIDIA L4 24 GiB | B7: 24 | C7: 201 | D7: =C7/$B$9 | E7: Available in some zones
A9: [INPUT] Exchange rate (RUB per USD) | B9: 90
A10: Cloud.ru (SberCloud) - GPU Instances (price per 1 GPU/hour)
A11: GPU | B11: VRAM (GiB) | C11: Price (RUB/hr) | D11: Price (USD/hr) | E11: Note
A12: NVIDIA A100 80 GiB | B12: 80 | C12: 490 | D12: =C12/$B$9 | E12: ML Space / Evolution
A13: NVIDIA T4 16 GiB | B13: 16 | C13: 120 | D13: =C13/$B$9 | E13: Basic GPU instance
A14: NVIDIA L4 24 GiB | B14: 24 | C14: 185 | D14: =C14/$B$9 | E14: Inference-optimized
A17: MONTHLY COST BY CONFIGURATION
A18: [INPUT] Hours per month: | B18: 730
A20: Configuration | B20: Num GPUs | C20: Yandex Cloud (RUB/mo) | D20: Cloud.ru (RUB/mo) | E20: Difference (RUB) | F20: Note
A21: FP16, A100-80 GiB | B21: ='1. Hardware Sizing'!D38 | C21: =B21*C5*$B$18 | D21: =B21*C12*$B$18 | E21: =C21-D21 | F21: GPUs from Sheet 1 (edit replicas there)
A22: INT4, A100-80 GiB | B22: ='1. Hardware Sizing'!D41 | C22: =B22*C5*$B$18 | D22: =B22*C12*$B$18 | E22: =C22-D22 | F22: OPTIMUM - edit replicas on Sheet 1
A23: INT4, L4-24 GiB | B23: ='1. Hardware Sizing'!D42 | C23: =B23*C7*$B$18 | D23: =B23*C14*$B$18 | E23: =C23-D23 | F23: GPUs from Sheet 1 (edit replicas there)
A24: INT4, T4-16 GiB | B24: ='1. Hardware Sizing'!D43 | C24: =B24*C6*$B$18 | D24: =B24*C13*$B$18 | E24: =C24-D24 | F24: GPUs from Sheet 1 (edit replicas there)

Sheet 3. Optimization
A1: OPTIMIZATION: BATCHING & vLLM
A3: Optimization techniques
A4: Technique | B4: Throughput gain | C4: Cost reduction | D4: Description
A5: Continuous Batching | B5: 2-4x | C5: 50-75% | D5: Batch requests dynamically; GPU util 30% -> 80%+
A6: vLLM (PagedAttention) | B6: 2-5x | C6: 50-80% | D6: Efficient KV Cache management; eliminates fragmentation
A7: vLLM + Continuous Batching | B7: 3-6x | C7: 65-85% | D7: Combined: PagedAttention + dynamic batching
A8: Speculative Decoding | B8: 1.5-2.5x | C8: 30-60% | D8: Draft model generates candidates, main verifies
A9: INT4 quantization (GPTQ/AWQ) | B9: 1.5-2x | C9: 50-70% | D9: 4x less VRAM; fewer GPUs needed
A12: COST FORECAST WITH OPTIMIZATION
A13: Cloud.ru A100 price (RUB/hr): | B13: ='2. Cloud Comparison'!C12 | C13: Hours/month: | D13: ='2. Cloud Comparison'!B18
A15: Scenario | B15: [INPUT] Num GPUs | C15: Cost (RUB/mo) | D15: Savings vs Baseline
A16: Baseline (from Sheet 1: INT4, A100-80) | B16: ='1. Hardware Sizing'!D41 | C16: =B16*$B$13*$D$13 | D16: ---
A17: [INPUT] + Continuous Batching | B17: 3 | C17: =B17*$B$13*$D$13 | D17: =1-C17/C16
A18: [INPUT] + vLLM (PagedAttention) | B18: 2 | C18: =B18*$B$13*$D$13 | D18: =1-C18/C16
A19: [INPUT] + vLLM + Batching + INT4 | B19: 2 | C19: =B19*$B$13*$D$13 | D19: =1-C19/C16
A21: KEY INSIGHT:
A22: Adjust GPU counts above to model your optimization scenario. Cost and savings update automatically.

Sheet 4. Recommendation
A1: RECOMMENDATION DASHBOARD
A2: All numeric values update automatically from Sheets 1-3
A3: Parameter | B3: Value
A4: --- VRAM Summary ---
A5: Total VRAM: FP16 (GiB) | B5: ='1. Hardware Sizing'!B23
A6: Total VRAM: INT4 (GiB) | B6: ='1. Hardware Sizing'!C23
A7: VRAM reduction (FP16 / INT4) | B7: ='1. Hardware Sizing'!B23/'1. Hardware Sizing'!C23
A9: --- GPU Requirements (INT4, A100-80) ---
A10: GPUs per replica | B10: ='1. Hardware Sizing'!B41
A11: Replicas | B11: ='1. Hardware Sizing'!C41
A12: Total GPUs | B12: ='1. Hardware Sizing'!D41
A14: --- Monthly Cost (Cloud.ru, RUB) ---
A15: Cost: no optimization | B15: ='3. Optimization'!C16
A16: Cost: with vLLM + Batching + INT4 | B16: ='3. Optimization'!C19
A17: Savings (RUB/month) | B17: ='3. Optimization'!C16-'3. Optimization'!C19
A18: Savings % | B18: ='3. Optimization'!D19
A20: --- Qualitative Recommendations ---
A21: Inference Engine | B21: vLLM with PagedAttention + Continuous Batching
A22: Quantization | B22: INT4 (GPTQ or AWQ)
A23: Quality impact | B23: INT4 (AWQ/GPTQ) quality loss <1% on benchmarks
A24: Cloud provider | B24: Cloud.ru (SberCloud) - compare on Sheet 2
